ingresso/__init__.py
ingresso/ingresso.py
ingresso-0.1.5.dist-info/LICENSE
ingresso-0.1.5.dist-info/METADATA
ingresso-0.1.5.dist-info/WHEEL
ingresso-0.1.5.dist-info/RECORD
