Metadata-Version: 2.1
Name: ingresso
Version: 0.1.5
Summary: A wrapper python para o ingresso.com
Home-page: https://github.com/hudsonbrendon/ingresso.com#readme
License: MIT
Author: Hudson Brendon
Author-email: contato.hudsonbrendon@gmail.com
Requires-Python: >=3.9,<4.0
Classifier: License :: OSI Approved :: MIT License
Classifier: Programming Language :: Python :: 3
Classifier: Programming Language :: Python :: 3.9
Classifier: Programming Language :: Python :: 3.10
Classifier: Programming Language :: Python :: 3.11
Classifier: Programming Language :: Python :: 3.12
Classifier: Programming Language :: Python :: 3.13
Requires-Dist: requests (>=2.28.1,<3.0.0)
Project-URL: Repository, https://github.com/hudsonbrendon/ingresso.com
